{"metadata":{"dist-tags":{"latest":"2.0.4"},"versions":{"1.0.0":{"name":"@protobufjs/codegen","dist":{"tarball":"https://registry.npmjs.org/@protobufjs/codegen/-/codegen-1.0.0.tgz"},"scripts":{}},"1.0.1":{"name":"@protobufjs/codegen","dist":{"tarball":"https://registry.npmjs.org/@protobufjs/codegen/-/codegen-1.0.1.tgz"},"scripts":{}},"1.0.2":{"name":"@protobufjs/codegen","dist":{"tarball":"https://registry.npmjs.org/@protobufjs/codegen/-/codegen-1.0.2.tgz"},"scripts":{}},"1.0.3":{"name":"@protobufjs/codegen","dist":{"tarball":"https://registry.npmjs.org/@protobufjs/codegen/-/codegen-1.0.3.tgz"},"scripts":{}},"1.0.4":{"name":"@protobufjs/codegen","dist":{"tarball":"https://registry.npmjs.org/@protobufjs/codegen/-/codegen-1.0.4.tgz"},"scripts":{}},"1.0.5":{"name":"@protobufjs/codegen","dist":{"tarball":"https://registry.npmjs.org/@protobufjs/codegen/-/codegen-1.0.5.tgz"},"scripts":{}},"1.0.6":{"name":"@protobufjs/codegen","dist":{"tarball":"https://registry.npmjs.org/@protobufjs/codegen/-/codegen-1.0.6.tgz"},"scripts":{}},"1.0.7":{"name":"@protobufjs/codegen","dist":{"tarball":"https://registry.npmjs.org/@protobufjs/codegen/-/codegen-1.0.7.tgz"},"scripts":{}},"1.0.8":{"name":"@protobufjs/codegen","dist":{"tarball":"https://registry.npmjs.org/@protobufjs/codegen/-/codegen-1.0.8.tgz"},"scripts":{}},"2.0.0":{"name":"@protobufjs/codegen","dist":{"tarball":"https://registry.npmjs.org/@protobufjs/codegen/-/codegen-2.0.0.tgz"},"scripts":{}},"2.0.1":{"name":"@protobufjs/codegen","dist":{"tarball":"https://registry.npmjs.org/@protobufjs/codegen/-/codegen-2.0.1.tgz"},"scripts":{}},"2.0.2":{"name":"@protobufjs/codegen","dist":{"tarball":"https://registry.npmjs.org/@protobufjs/codegen/-/codegen-2.0.2.tgz"},"scripts":{}},"2.0.3":{"name":"@protobufjs/codegen","dist":{"tarball":"https://registry.npmjs.org/@protobufjs/codegen/-/codegen-2.0.3.tgz"},"scripts":{}},"2.0.4":{"name":"@protobufjs/codegen","dist":{"tarball":"https://registry.npmjs.org/@protobufjs/codegen/-/codegen-2.0.4.tgz"}}}},"etag":"W/\"e2878802964a00be576ff120166c145d\"","lastModified":"Sun, 12 Jun 2022 22:53:40 GMT"}
