{"metadata":{"dist-tags":{"latest":"4.0.0"},"versions":{"0.1.0":{"name":"term-size","dist":{"tarball":"https://registry.npmjs.org/term-size/-/term-size-0.1.0.tgz"},"scripts":{"test":"xo && ava"},"dependencies":{"execa":"^0.4.0"}},"0.1.1":{"name":"term-size","dist":{"tarball":"https://registry.npmjs.org/term-size/-/term-size-0.1.1.tgz"},"scripts":{"test":"xo && ava"},"dependencies":{"execa":"^0.4.0"}},"1.0.0":{"name":"term-size","dist":{"tarball":"https://registry.npmjs.org/term-size/-/term-size-1.0.0.tgz"},"scripts":{"test":"xo && ava"},"dependencies":{"execa":"^0.6.3"}},"1.1.0":{"name":"term-size","dist":{"tarball":"https://registry.npmjs.org/term-size/-/term-size-1.1.0.tgz"},"scripts":{"test":"xo && ava"},"dependencies":{"execa":"^0.6.3"}},"1.2.0":{"name":"term-size","dist":{"tarball":"https://registry.npmjs.org/term-size/-/term-size-1.2.0.tgz"},"scripts":{"test":"xo && ava"},"dependencies":{"execa":"^0.7.0"}},"2.0.0":{"name":"term-size","dist":{"tarball":"https://registry.npmjs.org/term-size/-/term-size-2.0.0.tgz"},"scripts":{"test":"xo && ava && tsd"},"dependencies":{"execa":"^1.0.0"}},"2.1.0":{"name":"term-size","dist":{"tarball":"https://registry.npmjs.org/term-size/-/term-size-2.1.0.tgz"},"scripts":{"test":"xo && ava && tsd"}},"2.1.1":{"name":"term-size","dist":{"tarball":"https://registry.npmjs.org/term-size/-/term-size-2.1.1.tgz"},"scripts":{"test":"xo && ava && tsd"}},"2.2.0":{"name":"term-size","dist":{"tarball":"https://registry.npmjs.org/term-size/-/term-size-2.2.0.tgz"},"scripts":{"test":"xo && ava && tsd"}},"2.2.1":{"name":"term-size","dist":{"tarball":"https://registry.npmjs.org/term-size/-/term-size-2.2.1.tgz"},"scripts":{"test":"xo && ava && tsd"}},"3.0.0":{"name":"term-size","dist":{"tarball":"https://registry.npmjs.org/term-size/-/term-size-3.0.0.tgz"},"scripts":{"test":"xo && ava && tsd"}},"3.0.1":{"name":"term-size","dist":{"tarball":"https://registry.npmjs.org/term-size/-/term-size-3.0.1.tgz"},"scripts":{"test":"xo && ava && tsd"}},"3.0.2":{"name":"term-size","dist":{"tarball":"https://registry.npmjs.org/term-size/-/term-size-3.0.2.tgz"},"scripts":{"test":"xo && ava && tsd"}},"4.0.0":{"name":"term-size","dist":{"tarball":"https://registry.npmjs.org/term-size/-/term-size-4.0.0.tgz"},"scripts":{"test":"xo && ava && tsd"},"deprecated":"Renamed to terminal-size"}}},"etag":"W/\"a492afb26bd6b0f4155b5451447b8a9d\"","lastModified":"Sat, 04 Nov 2023 17:51:21 GMT"}
